optoConfig96/__init__.py
optoConfig96/__main__.py
optoConfig96/application.py
optoConfig96/assistants.py
optoConfig96/config.py
optoConfig96/constants.py
optoConfig96/custom_traits.py
optoConfig96/experiment_csv.py
optoConfig96/export.py
optoConfig96/hardware.py
optoConfig96/load.py
optoConfig96/plates.py
optoConfig96/plots.py
optoConfig96/programs.py
optoConfig96/resources.py
optoConfig96/steps.py
optoConfig96/testmode.py
optoConfig96/ui.py
optoConfig96/utils.py
optoConfig96/version.py
optoConfig96/editors/MPLFigureEditor.py
optoConfig96/editors/__init__.py
optoConfig96/editors/bounds_editor.py
optoConfig96/editors/color_editor.py
optoConfig96/editors/range_editor.py
optoConfig96/editors/table_editor.py
optoConfig96/resources/LICENSE.txt
optoConfig96/resources/LICENSE_bundled.txt
optoConfig96/resources/appicon.png
optoConfig96/resources/arduino_template.cpp
optoConfig96/resources/docs/guide.css
optoConfig96/resources/docs/guide.md
optoConfig96/resources/docs/optoConfig96_guide.html
optoConfig96/resources/docs/images/bulk_assign_programs.jpg
optoConfig96/resources/docs/images/bulk_assign_wells.jpg
optoConfig96/resources/docs/images/corr_factors_sheet.jpg
optoConfig96/resources/docs/images/corr_factors_show.jpg
optoConfig96/resources/docs/images/export_csv.jpg
optoConfig96/resources/docs/images/interpolation_dialog.jpg
optoConfig96/resources/docs/images/interpolation_example.jpg
optoConfig96/resources/docs/images/overview.jpg
optoConfig96/resources/docs/images/plate_config.jpg
optoConfig96/resources/docs/images/programeditor.jpg
optoConfig96/resources/docs/images/setallparams.jpg
optoConfig96/resources/docs/images/simulation.jpg
optoConfig96/resources/docs/images/statusbar.jpg
optoConfig96/resources/docs/images/stepeditor.jpg
optoConfig96/resources/docs/images/well_colors.jpg
optoConfig96/resources/docs/images/annotated/bulk_assign.jpg
optoConfig96/resources/docs/images/annotated/overview.jpg
optoConfig96/resources/examples/3color_QCAll.op96
optoConfig96-1.0.5.dist-info/LICENSE.txt
optoConfig96-1.0.5.dist-info/LICENSE_bundled.txt
optoConfig96-1.0.5.dist-info/METADATA
optoConfig96-1.0.5.dist-info/WHEEL
optoConfig96-1.0.5.dist-info/top_level.txt
optoConfig96-1.0.5.dist-info/RECORD
