Metadata-Version: 2.1
Name: optoConfig96
Version: 1.0.5
Summary: A GUI tool to configure optoPlate96 experiments
Home-page: https://github.com/WeberSynBioLab/optoConfig-96
Author: Oliver Thomas
Author-email: oliver.thomas@sgbm.uni-freiburg.de
Keywords: biology optogenetics optoplate gui
Classifier: Programming Language :: Python :: 3
Classifier: Programming Language :: Python :: 3.7
Classifier: Programming Language :: Python :: 3.8
Classifier: Programming Language :: Python :: 3.9
Classifier: Operating System :: OS Independent
Requires-Python: >=3.7,<3.10
License-File: LICENSE.txt
License-File: LICENSE_bundled.txt
Requires-Dist: traits (>=6.2.0)
Requires-Dist: traitsui (>=7.2.1)
Requires-Dist: PyQt5 (<=5.15.7,>=5.15.4)
Requires-Dist: pygments (>=2.9.0)
Requires-Dist: numpy (<=1.23.5,>=1.21.1)
Requires-Dist: matplotlib (>=3.4.2)
Provides-Extra: build
Requires-Dist: pyinstaller (>=5.7.0) ; extra == 'build'
